[{"meno":"nkôjk","priezvisko":"ljklj","tel_cislo":"kljkl","doklad":"","adresa":"","cena":111,"datum_prijatia":"12.11.2016","datum_odovzdania":"19.11.2016","znacka":"HEAD","typ":"rtzrtzhrt trgerg","spodna_hrana":"1,25","bocna_hrana":"88","vykonana_praca":"Veľký servis","id":1,"poznamka":"jljljlj"},{"meno":"nkôjk","priezvisko":"ljklj","tel_cislo":"kljkl","doklad":"","adresa":"","cena":111,"datum_prijatia":"12.11.2016","datum_odovzdania":"19.11.2016","znacka":"HEAD","typ":"rtzrtzhrt trgerg","spodna_hrana":"0,75","bocna_hrana":"88","vykonana_praca":"Voskovanie","id":1,"poznamka":"jljljlj"},{"meno":"nkôjk","priezvisko":"ljklj","tel_cislo":"kljkl","doklad":"","adresa":"","cena":111,"datum_prijatia":"12.11.2016","datum_odovzdania":"19.11.2016","znacka":"Line","typ":"rtzrtzhrt trgerg","spodna_hrana":"0,75","bocna_hrana":"86","vykonana_praca":"Malý servis","id":1,"poznamka":"jljljlj"}]